pygestor/__init__.py
pygestor/core_api.py
pygestor/dataset_wrapper.py
pygestor/utils.py
pygestor/datasets/__init__.py
pygestor/datasets/hf_parquet.py
pygestor/datasets/wikipedia.py
pygestor/datasets/wit_base.py
pygestor/webui/__init__.py
pygestor/webui/dataviewer.py
pygestor/webui/infoview.py
pygestor/webui/new_menu.py
pygestor/webui/styles.py
pygestor/webui/webui_utils.py
tests/__init__.py
tests/test_core.py
pygestor-0.2.1.dist-info/LICENSE.md
pygestor-0.2.1.dist-info/METADATA
pygestor-0.2.1.dist-info/WHEEL
pygestor-0.2.1.dist-info/top_level.txt
pygestor-0.2.1.dist-info/RECORD
