Metadata-Version: 2.1
Name: pygestor
Version: 0.2.1
Summary: A tool for dataset ingestion and management.
Home-page: https://github.com/rlsn/Pygestor
Author: Yumo Wang
Author-email: Yumo Wang <yumo1996@gmail.com>
Maintainer-email: Yumo Wang <yumo1996@gmail.com>
License: Copyright (c) 2024 rlsn
Project-URL: Homepage, https://github.com/rlsn/Ingestor
Project-URL: Documentation, https://github.com/rlsn/Ingestor
Project-URL: Repository, https://github.com/rlsn/Ingestor.git
Project-URL: Bug Tracker, https://github.com/rlsn/Ingestor/issues
Project-URL: Changelog, https://github.com/rlsn/Ingestor
Keywords: dataset,ingestion,management,machine learning
Classifier: Development Status :: 3 - Alpha
Classifier: Programming Language :: Python :: 3.11
Classifier: Intended Audience :: Developers
Requires-Python: >=3.11
License-File: LICENSE.md
Requires-Dist: pyarrow>=17.0.0
Requires-Dist: huggingface-hub>=0.24.5
Requires-Dist: pillow>=10.4.0
Requires-Dist: nicegui>=1.4.34
Requires-Dist: pyperclip>=1.9.0
Provides-Extra: cli
Provides-Extra: gui
Requires-Dist: nicegui; extra == "gui"
